pathresolver/__init__.py
pathresolver/exceptions.py
pathresolver/evaluator/__init__.py
pathresolver/evaluator/base.py
pathresolver/evaluator/find.py
pathresolver/resolver/__init__.py
pathresolver/resolver/base.py
pathresolver/resolver/key.py
pathresolver/resolver/multi.py
pathresolver/resolver/predicate.py
pathresolver/resolver/resolvers.py
pathresolver-0.2.2.dist-info/DESCRIPTION.rst
pathresolver-0.2.2.dist-info/METADATA
pathresolver-0.2.2.dist-info/metadata.json
pathresolver-0.2.2.dist-info/RECORD
pathresolver-0.2.2.dist-info/top_level.txt
pathresolver-0.2.2.dist-info/WHEEL
