Metadata-Version: 2.0
Name: pathresolver
Version: 0.2.2
Summary: Resolve paths within nested objects.
Home-page: https://github.com/Andrew-Crosio/pathresolver
Author: Andrew Crosio
Author-email: andrew@andrewcrosio.com
License: UNKNOWN
Platform: UNKNOWN
